{"cameraMode":{"drawMode":0,"name":"Shaded","section":"Shading Mode"},"sceneLighting":false,"audioPlay":false,"sceneViewState":{"m_AlwaysRefresh":false,"showFog":true,"showSkybox":false,"showFlares":true,"showImageEffects":true,"showParticleSystems":true,"showVisualEffectGraphs":true,"m_FxEnabled":true},"in2DMode":false,"pivot":{"x":-10.763703346252442,"y":6.471848487854004,"z":-17.67972755432129},"rotation":{"x":0.07215799391269684,"y":-0.905999481678009,"z":0.3938116729259491,"w":0.14647269248962403},"size":9.564657211303711,"orthographic":false}